aipkgs_twilio/__init__.py
aipkgs_twilio/helpers.py
aipkgs_twilio-1.0.5.dist-info/LICENSE.md
aipkgs_twilio-1.0.5.dist-info/METADATA
aipkgs_twilio-1.0.5.dist-info/WHEEL
aipkgs_twilio-1.0.5.dist-info/RECORD
