Metadata-Version: 2.1
Name: aipkgs-twilio
Version: 1.0.5
Summary: Twilio package
Home-page: https://gitlab.com/aipy/public/packages.git
License: MIT
Keywords: ai
Author: Alexy
Author-email: alexy.ib@outlook.com
Requires-Python: >=3.11.4,<4.0.0
Classifier: License :: OSI Approved :: MIT License
Classifier: Programming Language :: Python :: 3
Classifier: Programming Language :: Python :: 3.12
Requires-Dist: twilio (>=9.0.5,<10.0.0)
Project-URL: Repository, https://gitlab.com/aipy/public/packages.git
